docstring_to_text/___package_meta.py
docstring_to_text/__init__.py
docstring_to_text-1.0.3.dist-info/METADATA
docstring_to_text-1.0.3.dist-info/WHEEL
docstring_to_text-1.0.3.dist-info/licenses/LICENSE.md
docstring_to_text-1.0.3.dist-info/RECORD
