Metadata-Version: 2.4
Name: docstring-to-text
Version: 1.0.3
Summary: A simple pip package converting docstrings into clean text (proper paragraphs and indents)
Project-URL: Source Code, https://github.com/Lex-DRL/Py-docstring-to-text
Project-URL: Issues, https://github.com/Lex-DRL/Py-docstring-to-text/issues
Author: Lex Darlog (Lex-DRL)
License-Expression: MPL-2.0
License-File: LICENSE.md
Classifier: License :: OSI Approved :: Mozilla Public License 2.0 (MPL 2.0)
Classifier: Operating System :: OS Independent
Classifier: Programming Language :: Python :: 3
Requires-Python: >=3.7
Provides-Extra: test
Requires-Dist: pytest; extra == 'test'
Requires-Dist: pytest-cov; extra == 'test'
